app.py
libraries.py
unit_test.py
srt_translator-0.1.0.dist-info/LICENSE
srt_translator-0.1.0.dist-info/METADATA
srt_translator-0.1.0.dist-info/WHEEL
srt_translator-0.1.0.dist-info/RECORD
